fetti/__about__.py
fetti/__init__.py
fetti/main.py
fetti-0.0.2.dist-info/METADATA
fetti-0.0.2.dist-info/WHEEL
fetti-0.0.2.dist-info/entry_points.txt
fetti-0.0.2.dist-info/licenses/LICENSE
fetti-0.0.2.dist-info/RECORD
