Metadata-Version: 2.4
Name: fetti
Version: 0.0.2
Summary: TOML-Powered Environment Injection.
Project-URL: Documentation, https://github.com/lykhvar/fetti#readme
Project-URL: Issues, https://github.com/lykhvar/fetti/issues
Project-URL: Source, https://github.com/lykhvar/fetti
Author-email: Artem Lykhvar <me@a10r.com>
License-Expression: MIT
License-File: LICENSE
Keywords: automation,cli,command-line,tooling,utility
Classifier: Development Status :: 3 - Alpha
Classifier: Programming Language :: Python
Classifier: Programming Language :: Python :: 3.11
Classifier: Programming Language :: Python :: 3.12
Classifier: Programming Language :: Python :: 3.13
Classifier: Programming Language :: Python :: Implementation :: CPython
Classifier: Programming Language :: Python :: Implementation :: PyPy
Requires-Python: >=3.11
Requires-Dist: click==8.2.1
